escrowai_jupyter/__init__.py
escrowai_jupyter/_version.py
escrowai_jupyter/handlers.py
escrowai_jupyter/main.py
escrowai_jupyter/static/escrowai-jupyter.css
escrowai_jupyter/static/extension.js
escrowai_jupyter-1.0.5.data/data/share/jupyter/labextensions/escrowai-jupyter/package.json
escrowai_jupyter-1.0.5.data/data/share/jupyter/labextensions/escrowai-jupyter/schemas/escrowai-jupyter/package.json.orig
escrowai_jupyter-1.0.5.data/data/share/jupyter/labextensions/escrowai-jupyter/schemas/escrowai-jupyter/plugin.json
escrowai_jupyter-1.0.5.data/data/share/jupyter/labextensions/escrowai-jupyter/static/339.d942aeab4712e4cb6aff.js
escrowai_jupyter-1.0.5.data/data/share/jupyter/labextensions/escrowai-jupyter/static/509.07cd9d4d2b41b99e0d35.js
escrowai_jupyter-1.0.5.data/data/share/jupyter/labextensions/escrowai-jupyter/static/728.6e3b01b4c83d4e755749.js
escrowai_jupyter-1.0.5.data/data/share/jupyter/labextensions/escrowai-jupyter/static/remoteEntry.f8af5b88571fb9e586f7.js
escrowai_jupyter-1.0.5.data/data/share/jupyter/labextensions/escrowai-jupyter/static/style.js
escrowai_jupyter-1.0.5.data/data/share/jupyter/labextensions/escrowai-jupyter/static/third-party-licenses.json
escrowai_jupyter-1.0.5.data/data/share/jupyter/labextensions/escrowai-jupyter/install.json
escrowai_jupyter-1.0.5.dist-info/METADATA
escrowai_jupyter-1.0.5.dist-info/WHEEL
escrowai_jupyter-1.0.5.dist-info/entry_points.txt
escrowai_jupyter-1.0.5.dist-info/licenses/LICENSE
escrowai_jupyter-1.0.5.dist-info/RECORD
