Metadata-Version: 2.4
Name: escrowai_jupyter
Version: 1.0.5
Dynamic: Keywords
Summary: An extension to encrypt and upload the working directory to EscrowAI
Project-URL: Homepage, https://github.com/BeeKeeperAI/escrowai-jupyter
Project-URL: Bug Tracker, https://github.com/BeeKeeperAI/escrowai-jupyter/issues
Project-URL: Repository, https://github.com/BeeKeeperAI/escrowai-jupyter.git
Author-email: Jacob Blum <jake.blum@beekeeperai.com>
License: BSD 3-Clause License
License-File: LICENSE
Classifier: Framework :: Jupyter
Classifier: Framework :: Jupyter :: JupyterLab
Classifier: Framework :: Jupyter :: JupyterLab :: 4
Classifier: Framework :: Jupyter :: JupyterLab :: Extensions
Classifier: Framework :: Jupyter :: JupyterLab :: Extensions :: Prebuilt
Classifier: License :: OSI Approved :: BSD License
Classifier: Programming Language :: Python
Classifier: Programming Language :: Python :: 3
Classifier: Programming Language :: Python :: 3.8
Classifier: Programming Language :: Python :: 3.9
Classifier: Programming Language :: Python :: 3.10
Classifier: Programming Language :: Python :: 3.11
Requires-Python: >=3.8
Requires-Dist: jupyter-server-proxy>=4.0.0
Requires-Dist: jupyter-server<2.16.0,>=2.0.0
